McScrp/__init__.py
McScrp-0.3.dist-info/METADATA
McScrp-0.3.dist-info/RECORD
McScrp-0.3.dist-info/WHEEL
McScrp-0.3.dist-info/top_level.txt
