Metadata-Version: 2.1
Name: McScrp
Version: 0.3
Summary: Simple Scrapping Library
Home-page: https://github.com/Medpy/McScraping
Author: CHAHBOUN Mohammed
Author-email: simomega42@gmail.com
License: UNKNOWN
Platform: UNKNOWN
Classifier: Programming Language :: Python :: 3
Classifier: License :: OSI Approved :: MIT License
Classifier: Operating System :: OS Independent
